MANIFEST.in
README.md
requirements.txt
setup.cfg
setup.py
google_screener_data_extract/__init__.py
google_screener_data_extract/google_screener_data_extract.py
google_screener_data_extract/jsonwebretrieve.py
google_screener_data_extract.egg-info/PKG-INFO
google_screener_data_extract.egg-info/SOURCES.txt
google_screener_data_extract.egg-info/dependency_links.txt
google_screener_data_extract.egg-info/requires.txt
google_screener_data_extract.egg-info/top_level.txt