Metadata-Version: 1.1
Name: google-screener-data-extract
Version: 0.0.2
Summary: Retreive stock data from google finance screener
Home-page: https://github.com/spidezad/google_screener_data_extract
Author: Tan Kok Hua
Author-email: UNKNOWN
License: BSD
Download-URL: https://github.com/spidezad/google_screener_data_extract/tarball/0.0.2
Platform: UNKNOWN
Classifier: Development Status :: 3 - Alpha
Classifier: Intended Audience :: Developers
Classifier: Programming Language :: Python :: 3
